efibootdude/__init__.py
efibootdude/main.py
efibootdude-2.0.0.dist-info/entry_points.txt
efibootdude-2.0.0.dist-info/licenses/LICENSE
efibootdude-2.0.0.dist-info/WHEEL
efibootdude-2.0.0.dist-info/METADATA
efibootdude-2.0.0.dist-info/RECORD
