Metadata-Version: 2.4
Name: efibootdude
Version: 2.0.0
Summary: A visual wrapper for efibootmgr
Keywords: app,installer,manager,appimages
Author-email: Joe Defen <joedef@duck.com>
Requires-Python: >=3.8
Classifier: Programming Language :: Python :: 3
Classifier: License :: OSI Approved :: MIT License
Classifier: Operating System :: POSIX :: Linux
License-File: LICENSE
Requires-Dist: importlib-metadata; python_version<"3.8"
Requires-Dist: console-window == 1.4.3
Project-URL: Bug Tracker, https://github.com/joedefen/efibootdude/issues
Project-URL: Homepage, https://github.com/joedefen/efibootdude
